LICENSE
limeutils/__init__.py
limeutils/db.py
limeutils/exceptions.py
limeutils/redis/__init__.py
limeutils/redis/models.py
limeutils/redis/red.py
limeutils/utils.py
limeutils-0.3.1.dist-info/LICENSE
limeutils-0.3.1.dist-info/METADATA
limeutils-0.3.1.dist-info/WHEEL
limeutils-0.3.1.dist-info/RECORD
